Metadata-Version: 1.1
Name: hope
Version: 0.7.1
Summary: A Python Just-In-Time compiler for astrophysical computations
Home-page: http://hope.phys.ethz.ch
Author: Lukas Gamper, Joel Akeret
Author-email: hope@phys.ethz.ch
License: GPLv3
Keywords: HOPE,JIT compiler,HPC,high performance computing
Platform: UNKNOWN
Classifier: Development Status :: 4 - Beta
Classifier: Intended Audience :: Science/Research
Classifier: Intended Audience :: Developers
Classifier: Intended Audience :: Information Technology
Classifier: License :: OSI Approved :: GNU General Public License v3 or later (GPLv3+)
Classifier: Natural Language :: English
Classifier: Operating System :: MacOS
Classifier: Operating System :: POSIX
Classifier: Programming Language :: Python :: 2.7
Classifier: Programming Language :: Python :: 3.3
Classifier: Programming Language :: Python :: 3.4
Classifier: Programming Language :: Python :: 3.5
Classifier: Programming Language :: Python :: 3.6
Classifier: Topic :: Scientific/Engineering
Classifier: Topic :: Scientific/Engineering :: Mathematics
Classifier: Topic :: Scientific/Engineering :: Physics
Classifier: Topic :: Software Development :: Code Generators
Classifier: Topic :: Software Development :: Compilers
